price_mapping/__init__.py
price_mapping/main.py
price_mapping/utilities.py
price_mapping-0.0.1.dist-info/METADATA
price_mapping-0.0.1.dist-info/WHEEL
price_mapping-0.0.1.dist-info/licenses/LICENSE
price_mapping-0.0.1.dist-info/RECORD
