Metadata-Version: 2.3
Name: price_mapping
Version: 0.0.1
Summary: A calculation package
Project-URL: Homepage, https://github.com/kevinkhang2909/core_tpl
Project-URL: Bug Tracker, https://github.com/kevinkhang2909/core_tpl/issues
Author-email: Kevin Khang <kevinkhang2909@gmail.com>
License: Copyright (c) 2024 Kevin Khang
License-File: LICENSE
Keywords: etl
Classifier: License :: OSI Approved :: MIT License
Classifier: Operating System :: OS Independent
Classifier: Programming Language :: Python :: 3
Requires-Python: >=3.10
Requires-Dist: duckdb
Requires-Dist: loguru
Requires-Dist: numpy
Requires-Dist: orjson
Requires-Dist: polars
Requires-Dist: pyarrow
Requires-Dist: tqdm
